adafruit_ble_heart_rate.py
adafruit_circuitpython_ble_heart_rate-1.1.23.dist-info/licenses/LICENSE
adafruit_circuitpython_ble_heart_rate-1.1.23.dist-info/METADATA
adafruit_circuitpython_ble_heart_rate-1.1.23.dist-info/WHEEL
adafruit_circuitpython_ble_heart_rate-1.1.23.dist-info/top_level.txt
adafruit_circuitpython_ble_heart_rate-1.1.23.dist-info/RECORD
